{
    "request": {
        "type": "City",
        "query": "London, United Kingdom",
        "language": "en",
        "unit": "m"
    },
    "location": {
        "name": "London",
        "country": "United Kingdom",
        "region": "City of London, Greater London",
        "lat": "51.517",
        "lon": "-0.106",
        "timezone_id": "Europe/London",
        "localtime": "2025-01-15 14:27",
        "localtime_epoch": 1736951220,
        "utc_offset": "0.0"
    },
    "current": {
        "observation_time": "02:27 PM",
        "temperature": 9,
        "weather_code": 143,
        "weather_icons": [
            "https://cdn.worldweatheronline.com/images/wsymbols01_png_64/wsymbol_0006_mist.png"
        ],
        "weather_descriptions": [
            "Mist"
        ],
        "wind_speed": 5,
        "wind_degree": 255,
        "wind_dir": "WSW",
        "pressure": 1033,
        "precip": 0,
        "humidity": 100,
        "cloudcover": 75,
        "feelslike": 9,
        "uv_index": 0,
        "visibility": 7,
        "is_day": "yes"
    }
}